TrafficLightController.v
`timescale 1ns / 1ps
module TrafficLightController (
    input clk,
    input reset,
    input pedestrian_req,
    input emergency,
    output reg red,
    output reg yellow,
    output reg green,
    output reg ped_red,
    output reg ped_green
);

// State encoding
parameter RED = 0, RED_YELLOW = 1, GREEN = 2, YELLOW = 3,
          PED_GREEN = 4, EMERGENCY_GREEN = 5;

reg [2:0] state, next_state;
reg [3:0] timer;  // For delays

// FSM State Transition and Timer update
always @(posedge clk or posedge reset) begin
    if (reset) begin
        state <= RED;
        timer <= 0;
    end else begin
        state <= next_state;
        if (timer > 0)
            timer <= timer - 1;
    end
end

// Next state logic
always @(*) begin
    case(state)
        RED: begin
            if (emergency)
                next_state = EMERGENCY_GREEN;
            else if (timer == 0)
                next_state = RED_YELLOW;
            else
                next_state = RED;
        end

        RED_YELLOW: begin
            if (timer == 0)
                next_state = GREEN;
            else
                next_state = RED_YELLOW;
        end

        GREEN: begin
            if (emergency)
                next_state = EMERGENCY_GREEN;
            else if (timer == 0)
                next_state = YELLOW;
            else
                next_state = GREEN;
        end

        YELLOW: begin
            if (pedestrian_req)
                next_state = PED_GREEN;
            else if (timer == 0)
                next_state = RED;
            else
                next_state = YELLOW;
        end

        PED_GREEN: begin
            if (timer == 0)
                next_state = RED;
            else
                next_state = PED_GREEN;
        end

        EMERGENCY_GREEN: begin
            if (timer == 0)
                next_state = YELLOW;
            else
                next_state = EMERGENCY_GREEN;
        end

        default: next_state = RED;
    endcase
end

    // Output logic and timer load on state entry
    always @(posedge clk or posedge reset) begin
        if (reset) begin
            red <= 1;
            yellow <= 0;
            green <= 0;
            ped_red <= 1;
            ped_green <= 0;
            timer <= 4;
        end else begin
            case (state)
                RED: begin
                    red <= 1;
                    yellow <= 0;
                    green <= 0;
                    ped_red <= 1;
                    ped_green <= 0;
                    if (timer == 0)
                        timer <= 4;
                end

                RED_YELLOW: begin
                    red <= 1;
                    yellow <= 1;
                    green <= 0;
                    ped_red <= 1;
                    ped_green <= 0;
                    if (timer == 0)
                        timer <= 2;
                end

                GREEN: begin
                    red <= 0;
                    yellow <= 0;
                    green <= 1;
                    ped_red <= 1;
                    ped_green <= 0;
                    if (timer == 0)
                        timer <= 5;
                end

                YELLOW: begin
                    red <= 0;
                    yellow <= 1;
                    green <= 0;
                    ped_red <= 1;
                    ped_green <= 0;
                    if (timer == 0)
                        timer <= 3;
                end

                PED_GREEN: begin
                    red <= 1; // Keep cars at red
                    yellow <= 0;
                    green <= 0;
                    ped_red <= 0;
                    ped_green <= 1;
                    if (timer == 0)
                        timer <= 6; // Increased timer for pedestrian green
                end

                EMERGENCY_GREEN: begin
                    red <= 0;
                    yellow <= 0;
                    green <= 1; // Green for cars
                    ped_red <= 1;
                    ped_green <= 0;
                    if (timer == 0)
                        timer <= 6;
                end

                default: begin
                    red <= 1;
                    yellow <= 0;
                    green <= 0;
                    ped_red <= 1;
                    ped_green <= 0;
                    timer <= 4;
                end
            endcase
        end
    end

endmodule

TrafficLightController_tb.v
`timescale 1ns/1ps

module TrafficLightController_tb;

reg clk, reset;
reg pedestrian_req;
reg emergency;
wire red, yellow, green;
wire ped_red, ped_green;

TrafficLightController dut (
    .clk(clk),
    .reset(reset),
    .pedestrian_req(pedestrian_req),
    .emergency(emergency),
    .red(red),
    .yellow(yellow),
    .green(green),
    .ped_red(ped_red),
    .ped_green(ped_green)
);

initial clk = 0;
always #5 clk = ~clk; // 10ns clock

initial begin
    $dumpfile("TrafficLightController.vcd");
    $dumpvars(0, TrafficLightController_tb);

    reset = 1; #10;
    reset = 0;

    pedestrian_req = 0;
    emergency = 0;

    #50 pedestrian_req = 1; // Request pedestrian crossing
    #100 pedestrian_req = 0;

    #50 emergency = 1; // Emergency vehicle
    #30 emergency = 0;

    #400 $finish; // Run long enough to see state transitions
end

initial begin
    $monitor("At time %t: red=%b, yellow=%b, green=%b, ped_red=%b, ped_green=%b, pedestrian_req=%b, emergency=%b",
             $time, red, yellow, green, ped_red, ped_green, pedestrian_req, emergency);
end

endmodule

TrafficLightController.vcd
$date
	Wed Jun 11 00:49:40 2025
$end
$version
	Icarus Verilog
$end
$timescale
	1ps
$end
$scope module TrafficLightController_tb $end
$var wire 1 ! yellow $end
$var wire 1 " red $end
$var wire 1 # ped_red $end
$var wire 1 $ ped_green $end
$var wire 1 % green $end
$var reg 1 & clk $end
$var reg 1 ' emergency $end
$var reg 1 ( pedestrian_req $end
$var reg 1 ) reset $end
$scope module dut $end
$var wire 1 & clk $end
$var wire 1 ' emergency $end
$var wire 1 ( pedestrian_req $end
$var wire 1 ) reset $end
$var parameter 32 * EMERGENCY_GREEN $end
$var parameter 32 + GREEN $end
$var parameter 32 , PED_GREEN $end
$var parameter 32 - RED $end
$var parameter 32 . RED_YELLOW $end
$var parameter 32 / YELLOW $end
$var reg 1 % green $end
$var reg 3 0 next_state [2:0] $end
$var reg 1 $ ped_green $end
$var reg 1 # ped_red $end
$var reg 1 " red $end
$var reg 3 1 state [2:0] $end
$var reg 4 2 timer [3:0] $end
$var reg 1 ! yellow $end
$upscope $end
$upscope $end
$enddefinitions $end
$comment Show the parameter values. $end
$dumpall
b11 /
b1 .
b0 -
b100 ,
b10 +
b101 *
$end
#0
$dumpvars
b0 2
b0 1
b1 0
1)
x(
x'
0&
0%
0$
1#
1"
0!
$end
#5000
b0 0
b100 2
1&
#10000
0&
0'
0(
0)
#15000
b11 2
1&
#20000
0&
#25000
b10 2
1&
#30000
0&
#35000
b1 2
1&
#40000
0&
#45000
b1 0
b0 2
1&
#50000
0&
#55000
b1 1
b100 2
1&
#60000
0&
1(
#65000
1!
b11 2
1&
#70000
0&
#75000
b10 2
1&
#80000
0&
#85000
b1 2
1&
#90000
0&
#95000
b10 0
b0 2
1&
#100000
0&
#105000
b10 2
b10 1
1&
#110000
0&
#115000
b1 2
1%
0!
0"
1&
#120000
0&
#125000
b11 0
b0 2
1&
#130000
0&
#135000
b100 0
b11 1
b101 2
1&
#140000
0&
#145000
0%
1!
b100 2
b100 1
1&
#150000
0&
#155000
b11 2
1$
0#
0!
1"
1&
#160000
0&
0(
#165000
b10 2
1&
#170000
0&
#175000
b1 2
1&
#180000
0&
#185000
b0 0
b0 2
1&
#190000
0&
#195000
b0 1
b110 2
1&
#200000
0&
#205000
0$
1#
b101 2
1&
#210000
b101 0
0&
1'
#215000
b100 2
b101 1
1&
#220000
0&
#225000
1%
0"
b11 2
1&
#230000
0&
#235000
b10 2
1&
#240000
0&
0'
#245000
b1 2
1&
#250000
0&
#255000
b11 0
b0 2
1&
#260000
0&
#265000
b110 2
b11 1
1&
#270000
0&
#275000
b101 2
0%
1!
1&
#280000
0&
#285000
b100 2
1&
#290000
0&
#295000
b11 2
1&
#300000
0&
#305000
b10 2
1&
#310000
0&
#315000
b1 2
1&
#320000
0&
#325000
b0 0
b0 2
1&
#330000
0&
#335000
b0 1
b11 2
1&
#340000
0&
#345000
0!
1"
b10 2
1&
#350000
0&
#355000
b1 2
1&
#360000
0&
#365000
b1 0
b0 2
1&
#370000
0&
#375000
b1 1
b100 2
1&
#380000
0&
#385000
1!
b11 2
1&
#390000
0&
#395000
b10 2
1&
#400000
0&
#405000
b1 2
1&
#410000
0&
#415000
b10 0
b0 2
1&
#420000
0&
#425000
b10 2
b10 1
1&
#430000
0&
#435000
b1 2
1%
0!
0"
1&
#440000
0&
#445000
b11 0
b0 2
1&
#450000
0&
#455000
b11 1
b101 2
1&
#460000
0&
#465000
0%
1!
b100 2
1&
#470000
0&
#475000
b11 2
1&
#480000
0&
#485000
b10 2
1&
#490000
0&
#495000
b1 2
1&
#500000
0&
#505000
b0 0
b0 2
1&
#510000
0&
#515000
b0 1
b11 2
1&
#520000
0&
#525000
0!
1"
b10 2
1&
#530000
0&
#535000
b1 2
1&
#540000
0&
#545000
b1 0
b0 2
1&
#550000
0&
#555000
b1 1
b100 2
1&
#560000
0&
#565000
1!
b11 2
1&
#570000
0&
#575000
b10 2
1&
#580000
0&
#585000
b1 2
1&
#590000
0&
#595000
b10 0
b0 2
1&
#600000
0&
#605000
b10 2
b10 1
1&
#610000
0&
#615000
b1 2
1%
0!
0"
1&
#620000
0&
#625000
b11 0
b0 2
1&
#630000
0&
#635000
b11 1
b101 2
1&
